unofficialkeepsolidvpn/__init__.py
unofficialkeepsolidvpn-0.0.7.dist-info/LICENSE
unofficialkeepsolidvpn-0.0.7.dist-info/METADATA
unofficialkeepsolidvpn-0.0.7.dist-info/WHEEL
unofficialkeepsolidvpn-0.0.7.dist-info/top_level.txt
unofficialkeepsolidvpn-0.0.7.dist-info/RECORD
