Metadata-Version: 2.1
Name: unofficialkeepsolidvpn
Version: 0.0.7
Summary: unofficial keepsolid wireguard fetcher module
Home-page: https://github.com/Retch/keepsolid-vpn-wg-fetch
Author: Retch
Author-email: retch@mailpoof.com
License: GPL-3
Keywords: keepsolid
Classifier: Development Status :: 4 - Beta
Classifier: Intended Audience :: Developers
Classifier: License :: OSI Approved :: GNU General Public License v3 (GPLv3)
Classifier: Programming Language :: Python :: 3
License-File: LICENSE
Requires-Dist: selenium (>=3.141.0)
Requires-Dist: urllib3 (>=1.25.9)
Requires-Dist: requests (==2.26.0)
